.travis.yml
LICENSE
MANIFEST.in
Makefile
README.md
hello_led.py
pytest.ini
setup.py
docker/Dockerfile
examples/Makefile
examples/axi_stream_ultra96v2_pynq/Makefile
examples/axi_stream_ultra96v2_pynq/axi_stream.py
examples/axi_stream_ultra96v2_pynq/test_axi_stream.py
examples/axi_stream_ultra96v2_pynq/ultra96v2_pynq/README.md
examples/axi_stream_ultra96v2_pynq/ultra96v2_pynq/axi_stream.bit
examples/axi_stream_ultra96v2_pynq/ultra96v2_pynq/axi_stream.hwh
examples/axi_stream_ultra96v2_pynq/ultra96v2_pynq/axi_stream.v
examples/axi_stream_ultra96v2_pynq/ultra96v2_pynq/design_1.tcl
examples/axi_stream_ultra96v2_pynq/ultra96v2_pynq/run_on_pynq.ipynb
examples/axi_stream_ultra96v2_pynq/ultra96v2_pynq/run_on_pynq.py
examples/chatter_clear/Makefile
examples/chatter_clear/chatter_clear.py
examples/chatter_clear/test_chatter_clear.py
examples/counter/Makefile
examples/counter/counter.py
examples/counter/test_counter.py
examples/fifo_rtl/Makefile
examples/fifo_rtl/fifo_rtl.py
examples/fifo_rtl/test_fifo_rtl.py
examples/led/Makefile
examples/led/led.py
examples/led/test_led.py
examples/manyled/Makefile
examples/manyled/manyled.py
examples/manyled/test_manyled.py
examples/ram_rtl/Makefile
examples/ram_rtl/ram_rtl.py
examples/ram_rtl/test_ram_rtl.py
examples/read_verilog_code/Makefile
examples/read_verilog_code/read_verilog_code.py
examples/read_verilog_code/test_read_verilog_code.py
examples/regchain/Makefile
examples/regchain/regchain.py
examples/regchain/test_regchain.py
examples/simulation_verilator/Makefile
examples/simulation_verilator/simulation_verilator.py
examples/simulation_verilator/test_simulation_verilator.py
examples/sort/Makefile
examples/sort/sort.py
examples/sort/test_sort.py
examples/stream_axi_stream_fifo_ipxact_ultra96v2_pynq/Makefile
examples/stream_axi_stream_fifo_ipxact_ultra96v2_pynq/stream_axi_stream_fifo_ipxact.py
examples/stream_axi_stream_fifo_ipxact_ultra96v2_pynq/test_stream_axi_stream_fifo_ipxact.py
veriloggen.egg-info/PKG-INFO
veriloggen.egg-info/SOURCES.txt
veriloggen.egg-info/dependency_links.txt
veriloggen.egg-info/requires.txt
veriloggen.egg-info/top_level.txt
