Metadata-Version: 2.1
Name: veriloggen
Version: 2.3.0
Summary: A Mixed-Paradigm Hardware Construction Framework
Home-page: https://github.com/PyHDI/veriloggen
Author: Shinya Takamaeda-Yamazaki
License: Apache License 2.0
Keywords: FPGA,Verilog HDL,High-Level Synthesis
Provides-Extra: test
Provides-Extra: graph
License-File: LICENSE
